{
  "updatedAt": "2026-07-13T11:51:01.539Z",
  "eodUpdatedAt": "2026-07-10T12:11:47.104Z",
  "holdings": [
    "2330",
    "2317",
    "6669",
    "3017",
    "3324",
    "2382",
    "1519",
    "2308",
    "3231",
    "3661",
    "2356",
    "2376"
  ],
  "eod": [
    {
      "code": "1519",
      "name": "華城",
      "close": 721,
      "change": -19
    },
    {
      "code": "2308",
      "name": "台達電",
      "close": 1880,
      "change": -5
    },
    {
      "code": "2317",
      "name": "鴻海",
      "close": 237.5,
      "change": 0
    },
    {
      "code": "2330",
      "name": "台積電",
      "close": 2415,
      "change": -50
    },
    {
      "code": "2356",
      "name": "英業達",
      "close": 69.8,
      "change": 3.6
    },
    {
      "code": "2376",
      "name": "技嘉",
      "close": 336.5,
      "change": 1.5
    },
    {
      "code": "2382",
      "name": "廣達",
      "close": 373.5,
      "change": -3.5
    },
    {
      "code": "3017",
      "name": "奇鋐",
      "close": 2350,
      "change": 25
    },
    {
      "code": "3231",
      "name": "緯創",
      "close": 144.5,
      "change": -2
    },
    {
      "code": "3324",
      "name": "雙鴻",
      "close": 920,
      "change": -5
    },
    {
      "code": "3661",
      "name": "世芯-KY",
      "close": 4210,
      "change": 145
    },
    {
      "code": "6669",
      "name": "緯穎",
      "close": 5040,
      "change": -10
    }
  ],
  "valuation": {
    "1519": {
      "code": "1519",
      "pe": 49.55,
      "dividendYield": 1.66,
      "pbRatio": 27.65
    },
    "2308": {
      "code": "2308",
      "pe": 69.32,
      "dividendYield": 0.62,
      "pbRatio": 16.3
    },
    "2317": {
      "code": "2317",
      "pe": 16.87,
      "dividendYield": 3.02,
      "pbRatio": 1.87
    },
    "2330": {
      "code": "2330",
      "pe": 32.47,
      "dividendYield": 0.91,
      "pbRatio": 10.63
    },
    "2356": {
      "code": "2356",
      "pe": 26.54,
      "dividendYield": 2.87,
      "pbRatio": 3.41
    },
    "2376": {
      "code": "2376",
      "pe": 15.72,
      "dividendYield": 3.57,
      "pbRatio": 3.49
    },
    "2382": {
      "code": "2382",
      "pe": 18.78,
      "dividendYield": 4.18,
      "pbRatio": 6.94
    },
    "3017": {
      "code": "3017",
      "pe": 38.61,
      "dividendYield": 0.89,
      "pbRatio": 20.42
    },
    "3231": {
      "code": "3231",
      "pe": 14.49,
      "dividendYield": 3.81,
      "pbRatio": 2.42
    },
    "3324": {
      "code": "3324",
      "pe": 26.12,
      "dividendYield": 1.32,
      "pbRatio": 6.28
    },
    "3661": {
      "code": "3661",
      "pe": 61.7,
      "dividendYield": 0.81,
      "pbRatio": 7.95
    },
    "6669": {
      "code": "6669",
      "pe": 16.89,
      "dividendYield": 3.26,
      "pbRatio": 6.68
    }
  },
  "yield10y": {
    "date": "2026-07-09",
    "value": 4.54,
    "updatedAt": "2026-07-09T22:00:00.000Z",
    "source": "FRED DGS10 CSV"
  },
  "errors": [
    {
      "source": "TPEX OpenAPI daily close quotes",
      "message": "terminated"
    },
    {
      "source": "feed-preservation",
      "message": "kept 1 eod row(s), 0 valuation entr(ies) from previous feed due to upstream gaps"
    }
  ]
}
